{
    "50.0:250.0": "<src.blocks._blocks.NoneBlock object at 0x113a657d0>",
    "50.0:200.0": "<src.blocks._blocks.NoneBlock object at 0x113a65c50>",
    "50.0:150.0": "<src.blocks._blocks.NoneBlock object at 0x113a66110>",
    "50.0:100.0": "<src.blocks._blocks.NoneBlock object at 0x113a66390>",
    "50.0:50.0": "<src.blocks._blocks.NoneBlock object at 0x113a669d0>",
    "0.0:50.0": "<src.blocks._blocks.NoneBlock object at 0x1102802d0>",
    "0.0:0.0": "<src.blocks._blocks.NoneBlock object at 0x113a68790>",
    "0.0:100.0": "<src.blocks._blocks.NoneBlock object at 0x113a690d0>",
    "0.0:150.0": "<src.blocks._blocks.NoneBlock object at 0x113a6a410>",
    "0.0:200.0": "<src.blocks._blocks.NoneBlock object at 0x113a692d0>",
    "0.0:250.0": "<src.blocks._blocks.NoneBlock object at 0x113a6a7d0>",
    "0.0:300.0": "<src.blocks._blocks.NoneBlock object at 0x113a6a8d0>",
    "0.0:350.0": "<src.blocks._blocks.NoneBlock object at 0x113a6a9d0>",
    "0.0:400.0": "<src.blocks._blocks.NoneBlock object at 0x113a6aa90>",
    "0.0:450.0": "<src.blocks._blocks.NoneBlock object at 0x113a6ab10>",
    "50.0:450.0": "<src.blocks._blocks.NoneBlock object at 0x113a6acd0>",
    "50.0:400.0": "<src.blocks._blocks.NoneBlock object at 0x113a6ad90>",
    "50.0:350.0": "<src.blocks._blocks.NoneBlock object at 0x113a6ae10>",
    "50.0:300.0": "<src.blocks._blocks.NoneBlock object at 0x113a6af90>",
    "100.0:400.0": "<src.blocks._blocks.NoneBlock object at 0x113a6b010>",
    "100.0:450.0": "<src.blocks._blocks.NoneBlock object at 0x113a6b190>",
    "100.0:350.0": "<src.blocks._blocks.NoneBlock object at 0x113a6b250>",
    "100.0:300.0": "<src.blocks._blocks.NoneBlock object at 0x113a6b350>",
    "100.0:250.0": "<src.blocks._blocks.NoneBlock object at 0x113a6b490>",
    "100.0:200.0": "<src.blocks._blocks.NoneBlock object at 0x113a6b5d0>",
    "100.0:150.0": "<src.blocks._blocks.NoneBlock object at 0x113a6b690>",
    "100.0:100.0": "<src.blocks._blocks.NoneBlock object at 0x113a6b7d0>",
    "100.0:50.0": "<src.blocks._blocks.NoneBlock object at 0x113a6b8d0>",
    "100.0:0.0": "<src.blocks._blocks.NoneBlock object at 0x113a6b950>",
    "50.0:0.0": "<src.blocks._blocks.NoneBlock object at 0x113a6bb10>",
    "150.0:0.0": "<src.blocks._blocks.NoneBlock object at 0x113a6bbd0>",
    "200.0:0.0": "<src.blocks._blocks.NoneBlock object at 0x113a6bc50>",
    "150.0:50.0": "<src.blocks._blocks.NoneBlock object at 0x113a6be10>",
    "150.0:100.0": "<src.blocks._blocks.NoneBlock object at 0x113a6bed0>",
    "150.0:150.0": "<src.blocks._blocks.NoneBlock object at 0x113a6bfd0>",
    "200.0:150.0": "<src.blocks._blocks.NoneBlock object at 0x113a6c110>",
    "200.0:100.0": "<src.blocks._blocks.NoneBlock object at 0x113a6c210>",
    "200.0:50.0": "<src.blocks._blocks.NoneBlock object at 0x113a6c310>",
    "250.0:200.0": "<src.blocks._blocks.NoneBlock object at 0x113a6c410>",
    "300.0:150.0": "<src.blocks._blocks.NoneBlock object at 0x113a6c4d0>",
    "300.0:100.0": "<src.blocks._blocks.NoneBlock object at 0x113a6c650>",
    "300.0:50.0": "<src.blocks._blocks.NoneBlock object at 0x113a6c710>",
    "300.0:0.0": "<src.blocks._blocks.NoneBlock object at 0x113a6c810>",
    "250.0:0.0": "<src.blocks._blocks.NoneBlock object at 0x113a6c890>",
    "250.0:50.0": "<src.blocks._blocks.NoneBlock object at 0x113a6ca50>",
    "250.0:100.0": "<src.blocks._blocks.NoneBlock object at 0x113a6cb10>",
    "250.0:150.0": "<src.blocks._blocks.NoneBlock object at 0x113a6cc10>",
    "350.0:100.0": "<src.blocks._blocks.NoneBlock object at 0x113a6cd10>",
    "350.0:50.0": "<src.blocks._blocks.NoneBlock object at 0x113a6ce10>",
    "350.0:0.0": "<src.blocks._blocks.NoneBlock object at 0x113a6cf10>",
    "400.0:50.0": "<src.blocks._blocks.NoneBlock object at 0x113a6cf90>",
    "400.0:100.0": "<src.blocks._blocks.NoneBlock object at 0x113a6d110>",
    "450.0:100.0": "<src.blocks._blocks.NoneBlock object at 0x113a6d210>",
    "450.0:50.0": "<src.blocks._blocks.NoneBlock object at 0x113a6d350>",
    "450.0:0.0": "<src.blocks._blocks.NoneBlock object at 0x113a6d390>",
    "400.0:0.0": "<src.blocks._blocks.NoneBlock object at 0x113a6d490>",
    "450.0:150.0": "<src.blocks._blocks.NoneBlock object at 0x113a6d650>",
    "400.0:150.0": "<src.blocks._blocks.NoneBlock object at 0x113a6d6d0>",
    "350.0:150.0": "<src.blocks._blocks.NoneBlock object at 0x113a6d850>",
    "200.0:200.0": "<src.blocks._blocks.NoneBlock object at 0x113a6d950>",
    "150.0:200.0": "<src.blocks._blocks.NoneBlock object at 0x113a6d9d0>",
    "300.0:200.0": "<src.blocks._blocks.NoneBlock object at 0x113a6dad0>",
    "350.0:200.0": "<src.blocks._blocks.NoneBlock object at 0x113a6dbd0>",
    "400.0:200.0": "<src.blocks._blocks.NoneBlock object at 0x113a6dd50>",
    "450.0:200.0": "<src.blocks._blocks.NoneBlock object at 0x113a6de10>",
    "450.0:250.0": "<src.blocks._blocks.NoneBlock object at 0x113a6df10>",
    "400.0:250.0": "<src.blocks._blocks.NoneBlock object at 0x113a6dfd0>",
    "350.0:250.0": "<src.blocks._blocks.NoneBlock object at 0x113a6e150>",
    "300.0:250.0": "<src.blocks._blocks.NoneBlock object at 0x113a6e210>",
    "250.0:250.0": "<src.blocks._blocks.NoneBlock object at 0x113a6e2d0>",
    "200.0:250.0": "<src.blocks._blocks.NoneBlock object at 0x113a6e450>",
    "150.0:250.0": "<src.blocks._blocks.NoneBlock object at 0x113a6e510>",
    "150.0:300.0": "<src.blocks._blocks.NoneBlock object at 0x113a6e610>",
    "200.0:300.0": "<src.blocks._blocks.NoneBlock object at 0x113a6e6d0>",
    "250.0:300.0": "<src.blocks._blocks.NoneBlock object at 0x113a6e850>",
    "300.0:300.0": "<src.blocks._blocks.NoneBlock object at 0x113a6e950>",
    "350.0:300.0": "<src.blocks._blocks.NoneBlock object at 0x113a6ea50>",
    "400.0:300.0": "<src.blocks._blocks.NoneBlock object at 0x113a6ead0>",
    "450.0:300.0": "<src.blocks._blocks.NoneBlock object at 0x113a6ebd0>",
    "450.0:350.0": "<src.blocks._blocks.NoneBlock object at 0x113a6ed10>",
    "400.0:350.0": "<src.blocks._blocks.NoneBlock object at 0x113a6ee50>",
    "350.0:350.0": "<src.blocks._blocks.NoneBlock object at 0x113a6ef50>",
    "300.0:350.0": "<src.blocks._blocks.NoneBlock object at 0x113a6efd0>",
    "250.0:350.0": "<src.blocks._blocks.NoneBlock object at 0x113a6f110>",
    "200.0:350.0": "<src.blocks._blocks.NoneBlock object at 0x113a6f210>",
    "150.0:350.0": "<src.blocks._blocks.NoneBlock object at 0x113a6f310>",
    "150.0:400.0": "<src.blocks._blocks.NoneBlock object at 0x113a6f410>",
    "200.0:400.0": "<src.blocks._blocks.NoneBlock object at 0x113a6f4d0>",
    "250.0:400.0": "<src.blocks._blocks.NoneBlock object at 0x113a6f650>",
    "300.0:400.0": "<src.blocks._blocks.NoneBlock object at 0x113a6f710>",
    "350.0:400.0": "<src.blocks._blocks.NoneBlock object at 0x113a6f850>",
    "400.0:400.0": "<src.blocks._blocks.NoneBlock object at 0x113a6f910>",
    "450.0:400.0": "<src.blocks._blocks.NoneBlock object at 0x113a6f9d0>",
    "450.0:450.0": "<src.blocks._blocks.NoneBlock object at 0x113a6fb10>",
    "400.0:450.0": "<src.blocks._blocks.NoneBlock object at 0x113a6fbd0>",
    "350.0:450.0": "<src.blocks._blocks.NoneBlock object at 0x113a6fd10>",
    "300.0:450.0": "<src.blocks._blocks.NoneBlock object at 0x113a6fe10>",
    "250.0:450.0": "<src.blocks._blocks.NoneBlock object at 0x113a6fed0>",
    "200.0:450.0": "<src.blocks._blocks.NoneBlock object at 0x113a6ffd0>",
    "150.0:450.0": "<src.blocks._blocks.NoneBlock object at 0x113a70150>"
  }